boat_jit/__init__.py
boat_jit/boat_opt.py
boat_jit/operation_registry.py
boat_jit/fo_ol/__init__.py
boat_jit/fo_ol/meso.py
boat_jit/fo_ol/pgdo.py
boat_jit/fo_ol/vfo.py
boat_jit/fo_ol/vso.py
boat_jit/gm_ol/__init__.py
boat_jit/gm_ol/di.py
boat_jit/gm_ol/dm.py
boat_jit/gm_ol/dynamical_system.py
boat_jit/gm_ol/gda.py
boat_jit/gm_ol/ngd.py
boat_jit/gm_ol/sequential_ds.py
boat_jit/higher_jit/__init__.py
boat_jit/higher_jit/optim.py
boat_jit/higher_jit/patch.py
boat_jit/higher_jit/utils.py
boat_jit/na_ol/__init__.py
boat_jit/na_ol/cg.py
boat_jit/na_ol/fd.py
boat_jit/na_ol/foa.py
boat_jit/na_ol/hyper_gradient.py
boat_jit/na_ol/iad.py
boat_jit/na_ol/iga.py
boat_jit/na_ol/ns.py
boat_jit/na_ol/ptt.py
boat_jit/na_ol/rad.py
boat_jit/na_ol/rgt.py
boat_jit/na_ol/sequential_hg.py
boat_jit/utils/__init__.py
boat_jit/utils/op_utils.py
boat_jit-1.0.6.dist-info/LICENSE
boat_jit-1.0.6.dist-info/METADATA
boat_jit-1.0.6.dist-info/WHEEL
boat_jit-1.0.6.dist-info/top_level.txt
boat_jit-1.0.6.dist-info/RECORD
